estim8.py
models.py
optimizers.py
utils.py
visualization.py
estim8Beta-0.0.3.dist-info/LICENSE.txt
estim8Beta-0.0.3.dist-info/METADATA
estim8Beta-0.0.3.dist-info/WHEEL
estim8Beta-0.0.3.dist-info/top_level.txt
estim8Beta-0.0.3.dist-info/RECORD
